airflow_clickhouse_plugin_maxtar/__init__.py
airflow_clickhouse_plugin_maxtar/__version__.py
airflow_clickhouse_plugin_maxtar/hooks/__init__.py
airflow_clickhouse_plugin_maxtar/hooks/clickhouse_hook.py
airflow_clickhouse_plugin_maxtar/operators/__init__.py
airflow_clickhouse_plugin_maxtar/operators/clickhouse_operator.py
airflow_clickhouse_plugin_maxtar/sensors/__init__.py
airflow_clickhouse_plugin_maxtar/sensors/clickhouse_sql_sensor.py
airflow_clickhouse_plugin_maxtar-0.0.15.dist-info/LICENSE
airflow_clickhouse_plugin_maxtar-0.0.15.dist-info/METADATA
airflow_clickhouse_plugin_maxtar-0.0.15.dist-info/WHEEL
airflow_clickhouse_plugin_maxtar-0.0.15.dist-info/top_level.txt
airflow_clickhouse_plugin_maxtar-0.0.15.dist-info/RECORD
